ansible_repo/__init__.py
ansible_repo/ansible_repo.py
ansible_repo-1.0.4.dist-info/METADATA
ansible_repo-1.0.4.dist-info/WHEEL
ansible_repo-1.0.4.dist-info/entry_points.txt
ansible_repo-1.0.4.dist-info/top_level.txt
ansible_repo-1.0.4.dist-info/RECORD
