Metadata-Version: 2.1
Name: ansible-repo
Version: 1.0.4
Summary: UNKNOWN
Home-page: UNKNOWN
Author: di-dip-unistra
Author-email: di-dip@unistra.fr
Maintainer: di-dip-unistra
Maintainer-email: di-dip@unistra.fr
License: PSF
Keywords: ansible,git,unistra,Université de Strasbourg
Platform: UNKNOWN
Requires-Dist: docopt (==0.6.2)
